steemrecovery/__init__.py
steemrecovery/steemrecovery.py
steemrecovery/version.py
steemrecovery-0.1.2.dist-info/METADATA
steemrecovery-0.1.2.dist-info/RECORD
steemrecovery-0.1.2.dist-info/WHEEL
steemrecovery-0.1.2.dist-info/entry_points.txt
steemrecovery-0.1.2.dist-info/top_level.txt
